mojang/__init__.py
mojang/auth/account.py
mojang/auth/constants.py
mojang/auth/exceptions.py
mojang/auth/network.py
mojang/auth/__init__.py
MojangAuth-0.0.4.dist-info/DESCRIPTION.rst
MojangAuth-0.0.4.dist-info/METADATA
MojangAuth-0.0.4.dist-info/metadata.json
MojangAuth-0.0.4.dist-info/RECORD
MojangAuth-0.0.4.dist-info/top_level.txt
MojangAuth-0.0.4.dist-info/WHEEL
