Metadata-Version: 2.0
Name: MojangAuth
Version: 0.0.4
Summary: Provides an API wrapper for the Mojang authentication API
Home-page: https://github.com/gdude2002/MojangAuth
Author: Gareth Coles
Author-email: gdude2002@gmail.com
License: Artistic License 2.0
Platform: UNKNOWN
Requires: requests
